Metadata-Version: 2.1
Name: cpda
Version: 2024.10.24
Summary: cpda: CESM Paleoclimate Data Assimilation
Home-page: https://github.com/fzhu2e/cpda
Author: Feng Zhu
Author-email: fengzhu@ucar.edu
License: GPL3
Keywords: CESM,Paleoclimate Data Assimilation
Classifier: Natural Language :: English
Classifier: Programming Language :: Python :: 3.12
License-File: LICENSE
Requires-Dist: netCDF4
Requires-Dist: xarray
Requires-Dist: dask
Requires-Dist: nc-time-axis
Requires-Dist: colorama
Requires-Dist: tqdm
Requires-Dist: x4c-exp
